python_urbandict-0.3.14.dist-info/licenses/LICENSE
pyurbandict/__init__.py
pyurbandict/parse.py
python_urbandict-0.3.14.dist-info/METADATA
python_urbandict-0.3.14.dist-info/WHEEL
python_urbandict-0.3.14.dist-info/top_level.txt
python_urbandict-0.3.14.dist-info/RECORD
