Metadata-Version: 2.4
Name: python-urbandict
Version: 0.3.14
Summary: Python wrapper for the Urban Dictionary API.
Author-email: atbuy <buy@atbuy.dev>
License-Expression: MIT
Project-URL: Bug Tracker, https://github.com/atbuy/pyurbandict/issues
Project-URL: Source Code, https://github.com/atbuy/pyurbandict
Project-URL: CI/CD, https://github.com/atbuy/pyurbandict/actions
Keywords: urban,dictionary,api,wrapper,python
Requires-Python: >=3.10
License-File: LICENSE
Requires-Dist: requests==2.32.5
Provides-Extra: dev
Requires-Dist: pre-commit==4.5.1; extra == "dev"
Requires-Dist: ruff==0.14.10; extra == "dev"
Requires-Dist: tox==4.33.0; extra == "dev"
Requires-Dist: pytest==9.0.2; extra == "dev"
Requires-Dist: pytest-cov==7.0.0; extra == "dev"
Dynamic: license-file
